hive_progress_bar/__init__.py
hive_progress_bar-0.0.4.dist-info/LICENSE
hive_progress_bar-0.0.4.dist-info/METADATA
hive_progress_bar-0.0.4.dist-info/WHEEL
hive_progress_bar-0.0.4.dist-info/top_level.txt
hive_progress_bar-0.0.4.dist-info/RECORD
