Metadata-Version: 2.1
Name: hive-progress-bar
Version: 0.0.4
Summary: A small progress bar for iterating over a collection and showing progress.
Home-page: https://github.com/hive-one/hive-progress-bar
Author: Heinrich Malan
Author-email: heinrich@hive.one
License: UNKNOWN
Platform: UNKNOWN
Classifier: Programming Language :: Python :: 3
Classifier: License :: OSI Approved :: MIT License
Classifier: Operating System :: OS Independent
Requires-Python: >=3.6
